heare/ids/__init__.py
heare_ids-0.1.3.dist-info/LICENSE
heare_ids-0.1.3.dist-info/METADATA
heare_ids-0.1.3.dist-info/WHEEL
heare_ids-0.1.3.dist-info/RECORD
