Metadata-Version: 2.3
Name: heare-ids
Version: 0.1.3
Summary: Stripe-like tokens in pure-python with no dependencies.
License: MIT
Author: Sean Fitzgerald
Author-email: sean@fitzgeralds.me
Requires-Python: >=3.10,<4.0
Classifier: License :: OSI Approved :: MIT License
Classifier: Programming Language :: Python :: 3
Classifier: Programming Language :: Python :: 3.10
Classifier: Programming Language :: Python :: 3.11
Classifier: Programming Language :: Python :: 3.12
Classifier: Programming Language :: Python :: 3.13
